pysgd/__init__.py
pysgd/adaptations/__init__.py
pysgd/adaptations/adagrad.py
pysgd/adaptations/adam.py
pysgd/adaptations/constant.py
pysgd/objectives/__init__.py
pysgd/objectives/linear.py
pysgd/objectives/logistic.py
pysgd/objectives/stab_tang.py
pysgd/tests/__init__.py
pysgd/tests/objective_test.py
pysgd/tests/theta_test.py
pysgd-0.0.1a2.dist-info/DESCRIPTION.rst
pysgd-0.0.1a2.dist-info/METADATA
pysgd-0.0.1a2.dist-info/RECORD
pysgd-0.0.1a2.dist-info/WHEEL
pysgd-0.0.1a2.dist-info/metadata.json
pysgd-0.0.1a2.dist-info/top_level.txt
