Metadata-Version: 2.0
Name: pysgd
Version: 0.0.1a2
Summary: Stochastic gradient descent algorithms
Home-page: UNKNOWN
Author: Caleb Everett
Author-email: mail@calebeverett.io
License: MIT
Keywords: machine-learning gradient-descent
Platform: UNKNOWN
Classifier: Development Status :: 3 - Alpha
Classifier: Intended Audience :: Developers
Classifier: Intended Audience :: Science/Research
Classifier: Topic :: Scientific/Engineering :: Information Analysis
Classifier: License :: OSI Approved :: MIT License
Classifier: Programming Language :: Python :: 2.7
Classifier: Programming Language :: Python :: 3
Classifier: Programming Language :: Python :: 3.3
Classifier: Programming Language :: Python :: 3.4
Classifier: Programming Language :: Python :: 3.5
Requires-Dist: numpy
Provides-Extra: test
Requires-Dist: py-cov; extra == 'test'
Requires-Dist: pyplot; extra == 'test'
Requires-Dist: pytest; extra == 'test'
